lensepy/__init__.py
lensepy/css.py
lensepy/appli/__init__.py
lensepy/appli/VI_gui/VI_gui.py
lensepy/appli/VI_gui/config/a2A1920-160ucBAS_40282232.pfs
lensepy/appli/VI_gui/config/all_params.txt
lensepy/appli/VI_gui/config/appli.xml
lensepy/appli/VI_gui/config/camera.ini
lensepy/appli/VI_gui/config/camera_small.ini
lensepy/appli/VI_gui/lang/FR.txt
lensepy/appli/_app/app_utils.py
lensepy/appli/_app/lense_view.py
lensepy/appli/_app/main_manager.py
lensepy/appli/_app/main_view.py
lensepy/appli/_app/template_controller.py
lensepy/appli/_assets/LEnsE_IOGS.jpg
lensepy/appli/_docs/_algo.txt
lensepy/appli/_docs/_xml_appli.txt
lensepy/appli/cmos_gui/cmos_gui.py
lensepy/appli/cmos_gui/config/a2A1920-160ucBAS_40282232.pfs
lensepy/appli/cmos_gui/config/all_params.txt
lensepy/appli/cmos_gui/config/appli.xml
lensepy/appli/cmos_gui/config/cam_pfs.txt
lensepy/appli/cmos_gui/config/camera.ini
lensepy/appli/cmos_gui/config/camera_old.ini
lensepy/appli/cmos_gui/config/camera_small.ini
lensepy/appli/cmos_gui/lang/FR.txt
lensepy/appli/cmos_gui/tests/EMVA1288_Basler_a2A1920-160umBAS_preliminary.pdf
lensepy/appli/cmos_gui/tests/test.xlsx
lensepy/appli/cmos_gui/tests/test_25_10_25.xlsx
lensepy/appli/cmos_gui/tests/test_25_11_17_am.xlsx
lensepy/appli/cmos_gui/tests/test_25_11_17_pm_mono.xlsx
lensepy/appli/cmos_gui/tests/test_25_10/Basler_Mean.png
lensepy/appli/cmos_gui/tests/test_25_10/DarkSignal_vs_IntegrationTime.png
lensepy/appli/cmos_gui/tests/test_25_10/DarkSignal_vs_IntegrationTime_BASLER.png
lensepy/appli/cmos_gui/tests/test_25_10/Sigma_f_u.png
lensepy/appli/cmos_gui/tests/test_25_10/Sigma_f_u_BASLER.png
lensepy/appli/colorimetry/__init__.py
lensepy/appli/colorimetry/colorimetry.py
lensepy/appli/colorimetry/config/appli.xml
lensepy/appli/colorimetry/lang/FR.txt
lensepy/appli/image_processing_gui/image_processing_gui.py
lensepy/appli/image_processing_gui/robot.jpg
lensepy/appli/image_processing_gui/config/all_params.txt
lensepy/appli/image_processing_gui/config/appli.xml
lensepy-2.0.7.dist-info/METADATA
lensepy-2.0.7.dist-info/WHEEL
lensepy-2.0.7.dist-info/licenses/LICENCE
lensepy-2.0.7.dist-info/RECORD
