Metadata-Version: 2.4
Name: lensepy
Version: 2.0.7
Summary: LEnsE Package including scientific methods in photonics and graphical objects to implement a User Interface
Project-URL: Homepage, https://github.com/IOGS-LEnsE/lensepy
Author-email: Julien VILLEMEJANE <julien.villemejane@institutoptique.fr>
License-File: LICENCE
Classifier: License :: OSI Approved :: MIT License
Classifier: Operating System :: OS Independent
Classifier: Programming Language :: Python :: 3
Requires-Python: >=3.11
Requires-Dist: colour-science
Requires-Dist: matplotlib>=2.1
Requires-Dist: numpy>=2.1
Requires-Dist: pypylon>=4.1.0
Requires-Dist: pyqt6>=6.1
Requires-Dist: pyqtgraph>=0.12
Requires-Dist: pyserial
